secure_email/__init__.py
secure_email/sendmail.py
secure_email_lacsd-1.0.4.dist-info/LICENSE
secure_email_lacsd-1.0.4.dist-info/WHEEL
secure_email_lacsd-1.0.4.dist-info/METADATA
secure_email_lacsd-1.0.4.dist-info/RECORD
