Metadata-Version: 2.1
Name: secure-email-lacsd
Version: 1.0.4
Summary: This project allows sending STMP email over TLS using SSL.
Author-email: John Dyer <johndyer@lacsd.org>
Classifier: License :: OSI Approved :: MIT License
